luca/__init__.py
luca/luca.py
luca_llai-0.1.0.dist-info/LICENSE
luca_llai-0.1.0.dist-info/METADATA
luca_llai-0.1.0.dist-info/WHEEL
luca_llai-0.1.0.dist-info/entry_points.txt
luca_llai-0.1.0.dist-info/top_level.txt
luca_llai-0.1.0.dist-info/RECORD
