Metadata-Version: 2.1
Name: luca-llai
Version: 0.1.0
Summary: A brief description of the luca package.
Home-page: https://github.com/yourusername/luca_project
Author: LearnableLoopAI.com
Author-email: kobus78@gmail.com
Classifier: Programming Language :: Python :: 3
Classifier: License :: OSI Approved :: MIT License
Classifier: Operating System :: OS Independent
Requires-Python: >=3.6
License-File: LICENSE
Requires-Dist: pymdp
